<?xml version="1.0" encoding="UTF-8"?>
<resources>
    <string name="2912">Contatta lo scambio</string>
    <string name="2914">Confermato dallo scambio e risolto</string>
    <string name="2915">Exchange</string>
    <string name="2916">Impossibile ottenere gli scambi più esposti nell'ultima settimana</string>
    <string name="2917">L'interfaccia di ricerca dello scambio internazionale è anormale</string>
    <string name="2918">Interfaccia anomala della lista nera degli scambi internazionali</string>
    <string name="2919">Interfaccia anormale di scambio internazionale</string>
    <string name="2920">Collega lo scambio</string>
    <string name="2921">minuto</string>
    <string name="2922">Giorni/Casi</string>
    <string name="2923">persone</string>
    <string name="2925">Avete avviato la mediazione per i reclami dei clienti, la nostra piattaforma seguirà la questione con questo scambio di informazioni e riceverete una risposta entro cinque giorni lavorativi</string>
    <string name="BTJ_000058">Errore di connessione di rete, riprova più tardi.</string>
    <string name="BTJ_000059">Nome:</string>
    <string name="BTJ_000057">Importo del reclamo:</string>
    <string name="BTJ_000054">L'account di trading non può essere vuoto</string>
    <string name="BTJ_000055">Trader</string>
    <string name="BTJ_000052">La richiesta di reclamo non può essere vuota</string>
    <string name="BTJ_000053">Trading account:</string>
    <string name="BTJ_000050">Requisiti per i reclami:</string>
    <string name="BTJ_000051">Numero di telefono:</string>
    <string name="BTJ_000106">Il contenuto del reclamo non può essere vuoto</string>
    <string name="BTJ_000107">Caricamento dell'immagine non riuscito, si prega di caricare di nuovo.</string>
    <string name="BTJ_000104">Il reclamante non può essere vuoto</string>
    <string name="BTJ_000105">nterfaccia anomala della lista nera dei broker internazionali</string>
    <string name="BTJ_000069">Il contenuto è insignificante</string>
    <string name="BTJ_000102">L'interfaccia del centro utenti è anormale</string>
    <string name="BTJ_000103">L'interfaccia di ricerca dei broker internazionali è anormale</string>
    <string name="BTJ_000067">Attacco abusivo</string>
    <string name="BTJ_000100">Formato immagine non valido</string>
    <string name="BTJ_000068">Altri</string>
    <string name="BTJ_000101">Informazioni sull'immagine non valide</string>
    <string name="BTJ_000065">Truffa</string>
    <string name="BTJ_000066">Impossibile prelevare</string>
    <string name="BTJ_000063">altri esposizioni</string>
    <string name="BTJ_000064">Pubblicazione fallita</string>
    <string name="BTJ_000061">Praticante</string>
    <string name="BTJ_000062">Agente</string>
    <string name="BTJ_000060">Esposizione</string>
    <string name="BTJ_000108">Operazione non riuscita, riprova più tardi</string>
    <string name="BTJ_000109">Seleziona il motivo della segnalazione</string>
    <string name="BTJ_000117">verifica fallita</string>
    <string name="BTJ_000118">Operazione non riuscita, l'editore di mercato non corrente non ha il diritto di eseguire l'operazione</string>
    <string name="BTJ_000115">Piaciuto dall'utente</string>
    <string name="BTJ_000116">L'utente ha già condiviso</string>
    <string name="BTJ_000113">l'esposizione corrente è in fase di revisione, l'operazione non è temporaneamente consentita</string>
    <string name="BTJ_000114">L'esposizione attuale è stata bloccata, l'operazione non è temporaneamente consentita</string>
    <string name="BTJ_000078">rumors</string>
    <string name="BTJ_000111">Il tuo problema è stato risolto con successo, vai a controllare lo stato più recente.</string>
    <string name="BTJ_000079">Altri</string>
    <string name="BTJ_000112">Le informazioni sull'esposizione attuale sono state aggiornate, si prega di ricaricare</string>
    <string name="BTJ_000076">Pornografia</string>
    <string name="BTJ_000077">Plagio contenuto</string>
    <string name="BTJ_000110">L'interfaccia del broker internazionale è anormale</string>
    <string name="BTJ_000074">Contenuto irreale</string>
    <string name="BTJ_000075">Rivela privacy</string>
    <string name="BTJ_000072">Attacchi regionali</string>
    <string name="BTJ_000073">Discriminazione razziale</string>
    <string name="BTJ_000070">Truffa</string>
    <string name="BTJ_000071">forte slittamento</string>
    <string name="BTJ_000080">Attacco abusivo</string>
    <string name="BTJ_000119">Carica foto</string>
    <string name="BTJ_000007">Servizio clienti d'oltremare di WikiBit</string>
    <string name="BTJ_000128">Il broker associato non può essere vuoto</string>
    <string name="BTJ_000008">Avvia la mediazione</string>
    <string name="BTJ_000129">Errore di invocazione all'interfaccia</string>
    <string name="BTJ_000005">Centro di mediazione WikiBit</string>
    <string name="BTJ_000126">Il paese di rilascio non può essere vuoto</string>
    <string name="BTJ_000006">Oggetto</string>
    <string name="BTJ_000127">post IP non può essere vuoto</string>
    <string name="BTJ_000003">Problema</string>
    <string name="BTJ_000124">Il titolo è obbligatorio</string>
    <string name="BTJ_000004">Requisiti</string>
    <string name="BTJ_000125">Il contenuto è obbligatorio</string>
    <string name="BTJ_000001">Tempo</string>
    <string name="BTJ_000089">Errore durante l'acquisizione del post di protezione dell'opinione globale</string>
    <string name="BTJ_000122">La categoria non può essere vuota</string>
    <string name="BTJ_000002">Quantità</string>
    <string name="BTJ_000123">L'utente ha tolto mi piace</string>
    <string name="BTJ_000087">Pornografia</string>
    <string name="BTJ_000120">visualizzato dall'utente</string>
    <string name="BTJ_000088">Rivela privacy</string>
    <string name="BTJ_000121">Il publisher non può essere vuoto</string>
    <string name="BTJ_000085">Attacchi regionali</string>
    <string name="BTJ_000086">Discriminazione razziale</string>
    <string name="BTJ_000083">Truffa</string>
    <string name="BTJ_000084">Plagio contenuto</string>
    <string name="BTJ_000081">Il contenuto è insignificante</string>
    <string name="BTJ_000082">Contenuto irreale</string>
    <string name="BTJ_000090">Non sei autorizzato a visualizzare questo post</string>
    <string name="BTJ_000091">rumors</string>
    <string name="BTJ_000009">Contatta il broker</string>
    <string name="BTJ_000018">Il contenuto include informazioni sensibili,WikiBit ha già nascosto</string>
    <string name="BTJ_000019">Conferma broker, Risolto</string>
    <string name="BTJ_000016">Timeout risolto automaticamente, Risolto</string>
    <string name="BTJ_000017">Conferma utente, Risolto</string>
    <string name="BTJ_000014">Congratulazioni, sei entrato nel servizio diretto della tutela dei diritti, WikiBit comprenderà la situazione dal broker per tuo conto, il reclamo del cliente riceverà una risposta al 100% entro 5 giorni lavorativi.</string>
    <string name="BTJ_000015">in sospeso</string>
    <string name="BTJ_000012">Persona</string>
    <string name="BTJ_000013">Impossibile ritirarsi</string>
    <string name="BTJ_000010">Non è stato superato</string>
    <string name="BTJ_000098">Nessun commento trovato,riprova</string>
    <string name="BTJ_000131">I visitatori non sono autorizzati a postare</string>
    <string name="BTJ_000011">In corso</string>
    <string name="BTJ_000099">ID utente non può essere vuoto</string>
    <string name="BTJ_000132">Rinunciato</string>
    <string name="BTJ_000096">Parametro di richiesta non valido</string>
    <string name="BTJ_000097">Interfaccia di protezione dell'opinione pubblica</string>
    <string name="BTJ_000130">Forum per scambi, media blockchain, istituti di investimento e industria correlata al mining</string>
    <string name="BTJ_000094">Nessun post trovato</string>
    <string name="BTJ_000095">Richiesta non riuscita, riprova</string>
    <string name="BTJ_000092">Impossibile ottenere i broker più esposti nell'ultima settimana</string>
    <string name="BTJ_000093">Errore ricerca database  del numero massimo di ordinamento</string>
    <string name="BTJ_000029">Non approvato</string>
    <string name="BTJ_000027">Verificato</string>
    <string name="BTJ_000028">Rinuncio soluzione</string>
    <string name="BTJ_000025">Ripondi</string>
    <string name="BTJ_000026">Materiale supplementare</string>
    <string name="BTJ_000023">Ora</string>
    <string name="BTJ_000024">Risolto</string>
    <string name="BTJ_000021">Risposto</string>
    <string name="BTJ_000022">Centro tutela diritti WikiBit</string>
    <string name="BTJ_000020">giorno</string>
    <string name="BTJ_000038">Risolto</string>
    <string name="BTJ_000039">Requisiti tutela diritti</string>
    <string name="BTJ_000036">Numero di telefono</string>
    <string name="BTJ_000037">Tempo tutela diritti</string>
    <string name="BTJ_000034">Importo protezione dei diritti</string>
    <string name="BTJ_000035">Problemi tutela diritti</string>
    <string name="BTJ_000032">Conto delle transazioni</string>
    <string name="BTJ_000033">Avvio tutela diritti</string>
    <string name="BTJ_000030">E-mail</string>
    <string name="BTJ_000031">Nome utente</string>
    <string name="BTJ_000049">Impossibile aggiungere il follow-up</string>
    <string name="BTJ_000047">Il nome di apertura dell'account non può essere vuoto</string>
    <string name="BTJ_000048">Email:</string>
    <string name="BTJ_000045">Il numero di telefono non può essere vuoto</string>
    <string name="BTJ_000046">Il follow-up è stato completato. Fai clic su 'Conferma' per visualizzare lo stato.</string>
    <string name="BTJ_000043">Impossibile aggiungere informazioni sull'utente</string>
    <string name="BTJ_000044">È necessario caricare prove supplementari</string>
    <string name="BTJ_000041">Soggetto protezione dei diritti</string>
    <string name="BTJ_000042">Rispondi</string>
    <string name="BTJ_000040">Chiedi</string>
    <string name="3068">La mediazione è terminata, fare clic su conferma per aggiornare lo stato</string>
    <string name="12679">La mediazione rimane irrisolta</string>
    <string name="12680">Ci sono follow-up irrisolti per questo utente</string>
    <string name="19301">Broker</string>
    <string name="19302">Analista</string>
</resources>
