<?xml version="1.0" encoding="UTF-8"?>
<resources>
    <string name="2912">ติดต่อแลกเปลี่ยน</string>
    <string name="2914">ยืนยันโดยการแลกเปลี่ยนและแก้ไข</string>
    <string name="2915">Exchange</string>
    <string name="2916">ไม่สามารถรับการแลกเปลี่ยนที่เปิดเผยมากที่สุดในสัปดาห์ที่แล้ว</string>
    <string name="2917">อินเทอร์เฟซการค้นหาแลกเปลี่ยนระหว่างประเทศผิดปกติ</string>
    <string name="2918">อินเทอร์เฟซที่ผิดปกติของบัญชีดำแลกเปลี่ยนระหว่างประเทศ</string>
    <string name="2919">อินเตอร์เฟซที่ผิดปกติของการแลกเปลี่ยนระหว่างประเทศ</string>
    <string name="2920">กรุณาเชื่อมโยง Exchange</string>
    <string name="2921">นาที</string>
    <string name="2922">วัน / กรณี</string>
    <string name="2923">คน</string>
    <string name="2925">คุณได้เริ่มการไกล่เกลี่ยข้อร้องเรียนแล้ว แพลตฟอร์มของเราจะติดตามปัญหานี้กับ Exchange ที่เกี่ยวข้อง และคุณจะได้รับการตอบกลับภายในห้าวันทำการ</string>
    <string name="BTJ_000058">การเชื่อมต่อเครือข่ายผิดโปรดลองอีกครั้งในภายหลัง</string>
    <string name="BTJ_000059">ชื่อ:</string>
    <string name="BTJ_000057">จำนวนเรื่องร้องเรียน:</string>
    <string name="BTJ_000054">บัญชีการค้าต้องไม่ว่างเปล่า</string>
    <string name="BTJ_000055">โบรกเกอร์</string>
    <string name="BTJ_000052">คำขอร้องเรียนต้องไม่ว่างเปล่า</string>
    <string name="BTJ_000053">บัญชีซื้อขาย:</string>
    <string name="BTJ_000050">ข้อกำหนดการร้องเรียน:</string>
    <string name="BTJ_000051">เบอร์โทรศัพท์:</string>
    <string name="BTJ_000106">เนื้อหาการรายงานไม่สามารถเว้นว่างได้</string>
    <string name="BTJ_000107">การอัปโหลดรูปล้มเหลว โปรดอัปโหลดใหม่อีกครั้ง</string>
    <string name="BTJ_000104">จำเป็นต้องมีผู้แจ้ง</string>
    <string name="BTJ_000105">อินเตอร์เฟซนายหน้าซื้อขายหลักทรัพย์ระหว่างประเทศผิดปกติ</string>
    <string name="BTJ_000069">เนื้อหานี้ไม่มีความหมาย</string>
    <string name="BTJ_000102">ส่วนต่อประสานศูนย์ผู้ใช้ผิดปกติ</string>
    <string name="BTJ_000103">หน้าค้นหาหน้าค้นหาอินเทอร์เฟซผิดปกติอินเทอร์เฟซผิดปกติ</string>
    <string name="BTJ_000067">การกล่าวหาที่หยาบคาย</string>
    <string name="BTJ_000100">รูปแบบกราฟิกไม่ถูกต้อง</string>
    <string name="BTJ_000068">อื่น ๆ</string>
    <string name="BTJ_000101">ข้อมูลรูปภาพไม่ถูกต้อง</string>
    <string name="BTJ_000065">มีความเสี่ยงถูกโบรกเกอร์โกง</string>
    <string name="BTJ_000066">ปัญหาการถอนเงิน</string>
    <string name="BTJ_000063">การเปิดเผยข้อมูลอื่น ๆ</string>
    <string name="BTJ_000064">การเผยแพร่ล้มเหลว</string>
    <string name="BTJ_000061">ผู้ประกอบการ</string>
    <string name="BTJ_000062">ตัวแทนโบรกเกอร์</string>
    <string name="BTJ_000060">การเปิดเผย</string>
    <string name="BTJ_000108">ระบบการใช้งานล้มเหลวโปรดลองใหม่อีกครั้ง</string>
    <string name="BTJ_000109">โปรดเลือกเหตุผลสำหรับการแจ้งรายงาน</string>
    <string name="BTJ_000117">การยืนยันล้มเหลว</string>
    <string name="BTJ_000118">การดำเนินการล้มเหลวผู้เผยแพร่โฆษณาที่ไม่ใช่ตลาดปัจจุบันไม่มีสิทธิ์ดำเนินการ</string>
    <string name="BTJ_000115">ถูกใจ</string>
    <string name="BTJ_000116">ผู้ใช้มีการแชร์เรียบร้อยแล้ว</string>
    <string name="BTJ_000113">ขั้นตอนการเปิดเผยยังอยู่ระหว่างการตรวจสอบในขณะนี้</string>
    <string name="BTJ_000114">ฟังก์ชั่นการเปิดเผยในปัจจุบันยังไม่เปิดให้บริการค่ะ</string>
    <string name="BTJ_000078">ข่าวเล่าลือ</string>
    <string name="BTJ_000111">ปัญหาได้รับการแก้ไขแล้วโปรดตรวจสอบสถานะใหม่</string>
    <string name="BTJ_000079">อื่น ๆ</string>
    <string name="BTJ_000112">ข้อมูลการเปิดเผยในปัจจุบันได้ถูกอัปเดท โปรดรีเฟรชเพื่อเข้าดูใหม่อีกครั้ง</string>
    <string name="BTJ_000076">สื่อลามก</string>
    <string name="BTJ_000077">คัดลอกเนื้อหา</string>
    <string name="BTJ_000110">ข้อยกเว้นของอินเตอร์เฟซของเทรดเดอร์ในต่างประเทศ</string>
    <string name="BTJ_000074">เนื้อหาไม่ตรง</string>
    <string name="BTJ_000075">การเปิดเผยความเป็นส่วนตัว</string>
    <string name="BTJ_000072">การโจมตีทางภูมิภาค</string>
    <string name="BTJ_000073">การเหยียดเชื้อชาติ</string>
    <string name="BTJ_000070">มีความเสี่ยงถูกโบรกเกอร์โกง</string>
    <string name="BTJ_000071">Slippageขั้นรุนแรง</string>
    <string name="BTJ_000080">การกล่าวหาที่หยาบคาย</string>
    <string name="BTJ_000119">อัพโหลดภาพ</string>
    <string name="BTJ_000007">ฝ่ายบริการลูกค้าของ WikiBit ในต่างประเทศ</string>
    <string name="BTJ_000128">ท่านจำเป็นจะต้องมีโบรกเกอร์ที่่มีความเกี่ยวข้อง</string>
    <string name="BTJ_000008">เริ่มการไกล่เกลี่ย</string>
    <string name="BTJ_000129">ข้อผิดพลาดในการโทรอินเตอร์เฟส</string>
    <string name="BTJ_000005">ศูนย์ไกล่เกลี่ย WikiBit</string>
    <string name="BTJ_000126">จำเป็นต้องระบุภูมิภาคที่เผยแพร่</string>
    <string name="BTJ_000006">ผู้ร่วมไกล่เกลี่ย</string>
    <string name="BTJ_000127">การเผยแพร่ IP ไม่สามารถเว้นได้</string>
    <string name="BTJ_000003">ปัญหาการไกล่เกลี่ย</string>
    <string name="BTJ_000124">จำเป็นต้องระบุชื่อ</string>
    <string name="BTJ_000004">คำขอไกล่เกลี่ย</string>
    <string name="BTJ_000125">เนื้อหาไม่สามารถเว้นว่างได้</string>
    <string name="BTJ_000001">เวลาไกล่เกลี่ย</string>
    <string name="BTJ_000089">ยังไม่พบข้อมูลการกำกับดูแลใดๆที่ถูกต้อง</string>
    <string name="BTJ_000122">การจำแนกไม่สามารถเว้นว่างได้</string>
    <string name="BTJ_000002">จำนวนเงินที่ไกล่เกลี่ย</string>
    <string name="BTJ_000123">ยกเลิก</string>
    <string name="BTJ_000087">สื่อลามก</string>
    <string name="BTJ_000120">ผู้ใช้ได้ดูแล้ว</string>
    <string name="BTJ_000088">การเปิดเผยความเป็นส่วนตัว</string>
    <string name="BTJ_000121">จำเป็นต้องมีสำนักพิมพ์</string>
    <string name="BTJ_000085">การโจมตีทางภูมิภาค</string>
    <string name="BTJ_000086">การเหยียดเชื้อชาติ</string>
    <string name="BTJ_000083">มีความเสี่ยงถูกโบรกเกอร์โกง</string>
    <string name="BTJ_000084">คัดลอกเนื้อหา</string>
    <string name="BTJ_000081">เนื้อหานี้ไม่มีความหมาย</string>
    <string name="BTJ_000082">เนื้อหาไม่ตรง</string>
    <string name="BTJ_000090">ท่านไม่ได้รับอนุญาตให้เข้าถึงบทความนี้คะ</string>
    <string name="BTJ_000091">ข่าวเล่าลือ</string>
    <string name="BTJ_000009">ติดต่อโบรกเกอร์</string>
    <string name="BTJ_000018">เนื้อหานี้เกี่ยวข้องกับข้อมูลที่ละเอียดอ่อนและ WikiBit จะซ่อนมันไว้</string>
    <string name="BTJ_000019">การยืนยันโบรกเกอร์ ได้รับการแก้ไขแล้ว</string>
    <string name="BTJ_000016">การแก้ไขเกินเวลาอัตโนมัติ ได้รับการแก้ไขแล้ว</string>
    <string name="BTJ_000017">การยืนยันผู้ใช้ ได้รับการแก้ไขแล้ว</string>
    <string name="BTJ_000014">ขอแสดงความยินดีที่คุณได้เข้าสู่การคุ้มครองสิทธิ์โดยตรงเราจะสอบถามโบรกเกอร์เกี่ยวกับสถานการณ์นี้ ในนามของ WikiBit การร้องเรียนของลูกค้าจะได้รับการตอบกลับ 100% ภายใน 5 วันทำการ</string>
    <string name="BTJ_000015">อยู่ระหว่างการตรวจสอบ</string>
    <string name="BTJ_000012">บุคคล</string>
    <string name="BTJ_000013">ไม่สามารถถอนได้</string>
    <string name="BTJ_000010">ไม่ผ่าน</string>
    <string name="BTJ_000098">ไม่พบการคอมเม้นต์โปรดลองอีกครั้ง</string>
    <string name="BTJ_000131">ผู้เข้าเยี่ยมชมไม่อนุญาตให้มีการโพสต์</string>
    <string name="BTJ_000011">กำลังประมวลผล</string>
    <string name="BTJ_000099">ต้องระบุ ID ผู้ใช้</string>
    <string name="BTJ_000132">ละทิ้ง</string>
    <string name="BTJ_000096">พารามิเตอร์คำขอไม่ถูกต้อง</string>
    <string name="BTJ_000097">อินเทอร์เฟซการป้องกันสื่อมีความผิดปกติ</string>
    <string name="BTJ_000130">การแลกเปลี่ยนสื่อบล็อกเชน สถาบันการลงทุน วงการแลกเปลี่ยนอุตสาหกรรมที่เกี่ยวข้องกับการขุด</string>
    <string name="BTJ_000094">ไม่พบโพสต์นี้</string>
    <string name="BTJ_000095">คำเรียกร้องของท่านล้มเหลว โปรดลองใหม่อีกครั้ง</string>
    <string name="BTJ_000092">รับข้อมูลของผู้เผยแพร่ที่ล้มเหลวล่าสุดก่อนใคร</string>
    <string name="BTJ_000093">ไม่สามารถค้นหาหมายเลขจำนวนสูงสุดในฐานข้อมูล</string>
    <string name="BTJ_000029">Unapproved</string>
    <string name="BTJ_000027">Verified</string>
    <string name="BTJ_000028">ยกเลิกการแก้ไข</string>
    <string name="BTJ_000025">ตอบกลับ</string>
    <string name="BTJ_000026">เพิ่มรายละเอียด</string>
    <string name="BTJ_000023">ชั่วโมง</string>
    <string name="BTJ_000024">ถูกแก้ไขเรียบร้อยแล้ว</string>
    <string name="BTJ_000021">ตอบแล้ว</string>
    <string name="BTJ_000022">ศูนย์พิทักษ์สิทธิ WikiBit</string>
    <string name="BTJ_000020">วัน</string>
    <string name="BTJ_000038">ถูกแก้ไขเรียบร้อยแล้ว</string>
    <string name="BTJ_000039">ข้อกำหนดการคุ้มครองสิทธิ</string>
    <string name="BTJ_000036">หมายเลขโทรศัพท์เปิดบัญชี</string>
    <string name="BTJ_000037">เวลาคุ้มครองสิทธิ</string>
    <string name="BTJ_000034">จำนวนเงินคุ้มครอง</string>
    <string name="BTJ_000035">ปัญหาการคุ้มครองสิทธิ</string>
    <string name="BTJ_000032">เลขบัญชี</string>
    <string name="BTJ_000033">เริ่มต้นการคุ้มครองสิทธิ</string>
    <string name="BTJ_000030">อีเมลเปิดบัญชี</string>
    <string name="BTJ_000031">ชื่อบัญชี</string>
    <string name="BTJ_000049">เพิ่มการสอบถามล้มเหลว</string>
    <string name="BTJ_000047">ชื่อบัญชีต้องไม่ว่างเปล่า</string>
    <string name="BTJ_000048">อีเมล:</string>
    <string name="BTJ_000045">หมายเลขโทรศัพท์ต้องไม่ว่างเปล่า</string>
    <string name="BTJ_000046">ได้สิ้นสุดการถามหนึ่งต่อหนึ่ง คลิกเพื่อยืนยันและอัปเดตสถานะหนึ่งต่อหนึ่ง</string>
    <string name="BTJ_000043">การเพิ่มข้อมูลผู้ใช้ล้มเหลว</string>
    <string name="BTJ_000044">จะต้องอัพโหลดหลักฐานเพิ่มเติม</string>
    <string name="BTJ_000041">คุ้มครองสิทธิ</string>
    <string name="BTJ_000042">คำตอบ</string>
    <string name="BTJ_000040">ติดตามผล</string>
    <string name="3068">การไกล่เกลี่ยสิ้นสุดแล้ว คลิกยืนยันเพื่ออัปเดตสถานะ</string>
    <string name="12679">การไกล่เกลี่ยยังไม่ได้รับการแก้ไข</string>
    <string name="12680">มีการติดตามผลที่ยังไม่ได้แก้ไขสำหรับผู้ใช้รายนี้</string>
    <string name="19301">โบรกเกอร์</string>
    <string name="19302">นักวิเคราะห์</string>
</resources>
