<?xml version="1.0" encoding="UTF-8"?>
<resources>
    <string name="HBHC_200059">Мошенничество</string>
    <string name="HBHC_200055">Расовая дискриминация</string>
    <string name="HBHC_200056">Скопированный контент</string>
    <string name="HBHC_200057">Региональные нападки</string>
    <string name="HBHC_200058">Раскрытие конфиденциальности</string>
    <string name="HBHC_200051">Оскорбительные нападки</string>
    <string name="HBHC_200052">Другие</string>
    <string name="HBHC_200053">Порнография</string>
    <string name="HBHC_200054">Слухи</string>
    <string name="HBHC_200050">Недействительный контент</string>
    <string name="HBHC_200048">Мошенничество</string>
    <string name="HBHC_200049">Бессмысленное содержание</string>
    <string name="HBHC_200044">Расовая дискриминация</string>
    <string name="HBHC_200045">Скопированный контент</string>
    <string name="HBHC_200046">Региональные нападки</string>
    <string name="HBHC_200047">Раскрытие конфиденциальности</string>
    <string name="HBHC_200040">Вы не авторизованы для просмотра этой записи</string>
    <string name="HBHC_200041">Ошибка</string>
    <string name="HBHC_200042">Порнография</string>
    <string name="HBHC_200043">Слухи</string>
    <string name="HBHC_200037">Не удалось найти максимум в базе данных</string>
    <string name="HBHC_200038">Не удалось получить</string>
    <string name="HBHC_200039">Не найдено</string>
    <string name="HBHC_200033">Неисправность пользовательского интерфейса</string>
    <string name="HBHC_200034">Неисправность интерфейса защиты общественного мнения</string>
    <string name="HBHC_200035">Ничего не найдено, пожалуйста, попробуйте еще раз</string>
    <string name="HBHC_200036">Неверный запрос, пожалуйста, попробуйте еще раз</string>
    <string name="HBHC_200030">Требуется ввести логин</string>
    <string name="HBHC_200031">Недействительная графическая информация</string>
    <string name="HBHC_200032">Неверный графический формат</string>
    <string name="HBHC_200026">Неисправность интерфейса черного списка международных брокеров</string>
    <string name="HBHC_200027">Неисправность поискового интерфейса международного брокера</string>
    <string name="HBHC_200028">Не удалось загрузить изображения, повторите попытку</string>
    <string name="HBHC_200029">Неверный параметр запроса</string>
    <string name="HBHC_200022">Строка для жалобы не может быть пустым</string>
    <string name="HBHC_200023">Пожалуйста, выберите ниже варианты</string>
    <string name="HBHC_200024">Строка для введения имени доносчика не может быть пустым</string>
    <string name="HBHC_200025">Неисправность интерфейса международного брокера</string>
    <string name="HBHC_200020">Обновите, чтобы просмотреть последние разоблачения</string>
    <string name="HBHC_200021">Проблемы устранены, пожалуйста, проверьте состояние теперь</string>
    <string name="HBHC_200015">Просмотрено</string>
    <string name="HBHC_200136">Незавершенный</string>
    <string name="HBHC_200016">Не удалось выполнить операцию. Повторите попытку позже.</string>
    <string name="HBHC_200017">Операция недоступна для лиц не состоящих на данном рынке</string>
    <string name="HBHC_200018">Операция недоступна, данная публикация пока рассматривается</string>
    <string name="HBHC_200132">Время посредничества</string>
    <string name="HBHC_200099">Номер телефона</string>
    <string name="HBHC_200011">Проверка подлинности не установлена</string>
    <string name="HBHC_200133">Связаться с брокером</string>
    <string name="HBHC_200012">В избранное</string>
    <string name="HBHC_200134">Служба поддержки клиентов WikiFX за рубежом</string>
    <string name="HBHC_200013">Подписка отменена</string>
    <string name="HBHC_200135">Центр посредничества WikiFX</string>
    <string name="HBHC_200014">Успешно поделились</string>
    <string name="HBHC_200095">Сумма к страхованию</string>
    <string name="HBHC_200096">Срок защиты прав</string>
    <string name="HBHC_200130">Запрос на посредничество</string>
    <string name="HBHC_200097">Полное имя</string>
    <string name="HBHC_200131">Сумма посредничества</string>
    <string name="HBHC_200098">Счет сделки</string>
    <string name="HBHC_200010">Требуется загрузить изображения</string>
    <string name="HBHC_200091">Индивидуальный опрос закончен, нажмите подтвердить чтобы обновить ваш запрос</string>
    <string name="HBHC_200092">Правозащитный объект</string>
    <string name="HBHC_200093">Вопросы по защите прав</string>
    <string name="HBHC_200094">Требования к защите прав</string>
    <string name="HBHC_200019">Публикация разоблачений заблокирована, на данный момент операция недоступна</string>
    <string name="HBHC_200125">Невозможно снять</string>
    <string name="HBHC_200004">При публикации введение IP обязательно</string>
    <string name="HBHC_200005">Название брокера обязательно</string>
    <string name="HBHC_200126">Биржи, блокчейн медиа, инвестиционные институты, биржи, связанные с горнодобывающей промышленностью</string>
    <string name="HBHC_200127">Начать посредничество</string>
    <string name="HBHC_200006">Заголовок обязателен</string>
    <string name="HBHC_200128">Объект посредничества</string>
    <string name="HBHC_200007">Введите содержание</string>
    <string name="HBHC_200121">Ваша публикация обрабатывается</string>
    <string name="HBHC_200088">Дополнительные вопросы</string>
    <string name="HBHC_200122">Идет обработка</string>
    <string name="HBHC_200089">Номер телефона обязательно к заполнению</string>
    <string name="HBHC_200001">Незарегистрированные лица не могут оставлять сообщения</string>
    <string name="HBHC_200123">Не пройдено</string>
    <string name="HBHC_200002">Ошибка вызова интерфейса</string>
    <string name="HBHC_200124">Человек</string>
    <string name="HBHC_200003">Введение страны публикации обязательно</string>
    <string name="HBHC_200084">Фото-доказательства обязательно к загрузке</string>
    <string name="HBHC_200085">Не удалось добавить дополнительные вопросы</string>
    <string name="HBHC_200086">Не удалось добавить дополнительные вопросы</string>
    <string name="HBHC_200120">Вы успешно перешли в центр подачи заявок по защите прав, WikiFX проведет расследование и ответит вам в течение {0} рабочих дней</string>
    <string name="HBHC_200087">Ответить</string>
    <string name="HBHC_200080">Адрес почты:</string>
    <string name="HBHC_200081">Имя и фамилия обязательно к заполнению</string>
    <string name="HBHC_200082">Номер торгового счета обязательно к заполнению</string>
    <string name="HBHC_200083">Требования к жалобе обязательно к заполнению</string>
    <string name="HBHC_200090">Рассмотрена</string>
    <string name="HBHC_200129">Проблемы с посредничеством</string>
    <string name="HBHC_200008">Введение вида разоблачения обязательно</string>
    <string name="HBHC_200009">Введение отправителя обязательно</string>
    <string name="HBHC_200114">Подтверждено пользователем, уже решено</string>
    <string name="HBHC_200115">Подтверждено дилером, уже решено</string>
    <string name="HBHC_200110">Центр защиты прав WikiFX</string>
    <string name="HBHC_200077">Требования к жалобе:</string>
    <string name="HBHC_200111">дней</string>
    <string name="HBHC_200078">Сумма жалобы:</string>
    <string name="HBHC_200112">Час</string>
    <string name="HBHC_200079">Номер телефона:</string>
    <string name="HBHC_200113">По истечении срока решается автоматически, уже решено</string>
    <string name="HBHC_200073">Практикующие</string>
    <string name="HBHC_200074">Трейдер</string>
    <string name="HBHC_200075">Имя и фамилия:</string>
    <string name="HBHC_200076">Номер торгового счета:</string>
    <string name="HBHC_200070">Нет подключения к сети. Повторите попытку позже</string>
    <string name="HBHC_200071">Агент</string>
    <string name="HBHC_200072">Брокеры</string>
    <string name="HBHC_200103">Ответить</string>
    <string name="HBHC_200104">Unapproved</string>
    <string name="HBHC_200105">Verified</string>
    <string name="HBHC_200106">Отменить защиту прав</string>
    <string name="HBHC_200066">Другие разоблачения</string>
    <string name="HBHC_200100">Email</string>
    <string name="HBHC_200067">Частое проскальзывание</string>
    <string name="HBHC_200101">Одобрить начатие защиты прав</string>
    <string name="HBHC_200068">Разоблачение</string>
    <string name="HBHC_200102">Дополнительные материалы</string>
    <string name="HBHC_200069">Публикация не удалась</string>
    <string name="HBHC_200062">Оскорбительные нападки</string>
    <string name="HBHC_200063">Другие</string>
    <string name="HBHC_200064">Мошенничество</string>
    <string name="HBHC_200065">Невозможно вывести деньги</string>
    <string name="HBHC_200060">Бессмысленное содержание</string>
    <string name="HBHC_200061">Недействительный контент</string>
    <string name="HBHC_200107">Рассмотрена</string>
    <string name="HBHC_200108">Получен ответ</string>
    <string name="HBHC_200109">Этот контент включает конфиденциальную информацию, поэтому он скрыт WikiFX.</string>
    <string name="12656">Посредничество остается нерешенным</string>
    <string name="12657">У этого пользователя есть нерешенные запросы</string>
    <string name="14762">Прежде чем подать заявку на получение компенсации в центр EPC, должны вам напомнить, что любая информация, которую вы предоставляете, должна быть правдивой и действительной, если обнаружится, что предоставленная вами информация является ложной, центр EPC оставляет за собой право отаказать вам в компенсации.</string>
    <string name="14763">Если данный трейдер скрылся, центр EPC компенсирует вам фактическую потерю не превышая максимальной суммы, установленной нормы на каждого клиента.</string>
    <string name="14764">Период действия каждой компенсации</string>
    <string name="14765">{0} дн.</string>
    <string name="16465">100% посредничество в жалобах</string>
    <string name="16466">Ответ в рабочие дни</string>
    <string name="16467">100% жалобы решены</string>
    <string name="16468">Посредничество</string>
    <string name="16469">Посредничество со стороны службы поддержки клиентов</string>
    <string name="16470">{0} рабочих дней</string>
    <string name="16471">100% ответ службы поддержки клиентов</string>
    <string name="16472">100% посредничество</string>
    <string name="16473">Если у вас возник спор с этим брокером и вы попросите Центр EMC выступить посредником, эксклюзивный зарубежный посредник из центра EMC будет заниматься урегулированием споров.</string>
    <string name="16474">100% отклик</string>
    <string name="16475">Посредник будет следить за делом на протяжении всего процесса и давать отзывы в течение 7 рабочих дней.</string>
    <string name="16476">Бесплатно</string>
    <string name="16477">Центр EMC предоставляет бесплатные услуги по урегулированию жалоб клиентов.</string>
    <string name="16478">Прежде чем подавать заявку на получение бесплатной юридической помощи в EMC Center, убедитесь, что вся предоставленная вами информация является достоверной и действительной, и если предоставленная вами информация является мошеннической, EMC Center оставляет за собой право отменить ваше право на получение юридической помощи.</string>
    <string name="16480">Юридическая помощь EPS</string>
    <string name="16481">Юридическая помощь C</string>
    <string name="16482">USD</string>
    <string name="16485">Срок действия каждой заявки</string>
    <string name="16490">Макс. выплата {0} долл. США</string>
    <string name="16497">Если юридическая помощь была применена, она автоматически вступит в силу, когда будет совершена реальная торговля.</string>
    <string name="16498">Если брокер скрывается, EPC Center инициирует судебное разбирательство за границей, и авансовые претензии будут отмечены как верхний предел и не превышают фактические убытки. Из-за ограничения объема приема, юридическая помощь, кроме побега брокера, временно не будет предоставлена.</string>
    <string name="16499">Прежде чем вы подадите заявку на бесплатную юридическую помощь в EPC Center, EPC Center должен вас оповестить, что любая информация, которую вы вводите, должна быть достоверной и действительной. Если предоставленная вами информация окажется неверной, EPC Center оставляет за собой право отменить ваше право на получение юридической помощи.</string>
    <string name="16500">Предмет претензии на каждого покупателя</string>
    <string name="16627">минута</string>
    <string name="16682">Аналитик</string>
    <string name="16727">день/случай</string>
</resources>
